[
  {
    "filename": "aicte-india.org_641f328e_full.png",
    "path": "CSE\\out\\screenshots\\aicte-india.org_641f328e_full.png",
    "domain": "aicte-india.org_641f328e"
  },
  {
    "filename": "aiims.edu_e4c61c3e_full.png",
    "path": "CSE\\out\\screenshots\\aiims.edu_e4c61c3e_full.png",
    "domain": "aiims.edu_e4c61c3e"
  },
  {
    "filename": "airtel.com_c3fc1664_full.png",
    "path": "CSE\\out\\screenshots\\airtel.com_c3fc1664_full.png",
    "domain": "airtel.com_c3fc1664"
  },
  {
    "filename": "airtel.in_c9b45dca_full.png",
    "path": "CSE\\out\\screenshots\\airtel.in_c9b45dca_full.png",
    "domain": "airtel.in_c9b45dca"
  },
  {
    "filename": "arunachalpradesh.gov.in_03dcf4df_full.png",
    "path": "CSE\\out\\screenshots\\arunachalpradesh.gov.in_03dcf4df_full.png",
    "domain": "arunachalpradesh.gov.in_03dcf4df"
  },
  {
    "filename": "assam.gov.in_0dc3b091_full.png",
    "path": "CSE\\out\\screenshots\\assam.gov.in_0dc3b091_full.png",
    "domain": "assam.gov.in_0dc3b091"
  },
  {
    "filename": "bankofbaroda.in_c866ab7a_full.png",
    "path": "CSE\\out\\screenshots\\bankofbaroda.in_c866ab7a_full.png",
    "domain": "bankofbaroda.in_c866ab7a"
  },
  {
    "filename": "bharatpetroleum.in_828f1daf_full.png",
    "path": "CSE\\out\\screenshots\\bharatpetroleum.in_828f1daf_full.png",
    "domain": "bharatpetroleum.in_828f1daf"
  },
  {
    "filename": "bhimupi.org.in_625d21ca_full.png",
    "path": "CSE\\out\\screenshots\\bhimupi.org.in_625d21ca_full.png",
    "domain": "bhimupi.org.in_625d21ca"
  },
  {
    "filename": "bobibanking.com_ed76a2b5_full.png",
    "path": "CSE\\out\\screenshots\\bobibanking.com_ed76a2b5_full.png",
    "domain": "bobibanking.com_ed76a2b5"
  },
  {
    "filename": "bseindia.com_c666cf7d_full.png",
    "path": "CSE\\out\\screenshots\\bseindia.com_c666cf7d_full.png",
    "domain": "bseindia.com_c666cf7d"
  },
  {
    "filename": "bsnl.co.in_b862995c_full.png",
    "path": "CSE\\out\\screenshots\\bsnl.co.in_b862995c_full.png",
    "domain": "bsnl.co.in_b862995c"
  },
  {
    "filename": "cbse.gov.in_5fc35e8f_full.png",
    "path": "CSE\\out\\screenshots\\cbse.gov.in_5fc35e8f_full.png",
    "domain": "cbse.gov.in_5fc35e8f"
  },
  {
    "filename": "centralbankofindia.co.in_7b7baaff_full.png",
    "path": "CSE\\out\\screenshots\\centralbankofindia.co.in_7b7baaff_full.png",
    "domain": "centralbankofindia.co.in_7b7baaff"
  },
  {
    "filename": "cert-in.org.in_bf315547_full.png",
    "path": "CSE\\out\\screenshots\\cert-in.org.in_bf315547_full.png",
    "domain": "cert-in.org.in_bf315547"
  },
  {
    "filename": "chandigarh.gov.in_da080203_full.png",
    "path": "CSE\\out\\screenshots\\chandigarh.gov.in_da080203_full.png",
    "domain": "chandigarh.gov.in_da080203"
  },
  {
    "filename": "cris.org.in_01404dab_full.png",
    "path": "CSE\\out\\screenshots\\cris.org.in_01404dab_full.png",
    "domain": "cris.org.in_01404dab"
  },
  {
    "filename": "crsorgi.gov.in_1e14b51f_full.png",
    "path": "CSE\\out\\screenshots\\crsorgi.gov.in_1e14b51f_full.png",
    "domain": "crsorgi.gov.in_1e14b51f"
  },
  {
    "filename": "delhi.gov.in_dde073d8_full.png",
    "path": "CSE\\out\\screenshots\\delhi.gov.in_dde073d8_full.png",
    "domain": "delhi.gov.in_dde073d8"
  },
  {
    "filename": "dgft.gov.in_ca8a7992_full.png",
    "path": "CSE\\out\\screenshots\\dgft.gov.in_ca8a7992_full.png",
    "domain": "dgft.gov.in_ca8a7992"
  },
  {
    "filename": "digilocker.gov.in_9996b907_full.png",
    "path": "CSE\\out\\screenshots\\digilocker.gov.in_9996b907_full.png",
    "domain": "digilocker.gov.in_9996b907"
  },
  {
    "filename": "dnh.gov.in_3ec6ca8b_full.png",
    "path": "CSE\\out\\screenshots\\dnh.gov.in_3ec6ca8b_full.png",
    "domain": "dnh.gov.in_3ec6ca8b"
  },
  {
    "filename": "education.gov.in_df83fee1_full.png",
    "path": "CSE\\out\\screenshots\\education.gov.in_df83fee1_full.png",
    "domain": "education.gov.in_df83fee1"
  },
  {
    "filename": "epfindia.gov.in_3037960e_full.png",
    "path": "CSE\\out\\screenshots\\epfindia.gov.in_3037960e_full.png",
    "domain": "epfindia.gov.in_3037960e"
  },
  {
    "filename": "esic.nic.in_835b7bf7_full.png",
    "path": "CSE\\out\\screenshots\\esic.nic.in_835b7bf7_full.png",
    "domain": "esic.nic.in_835b7bf7"
  },
  {
    "filename": "fssai.gov.in_042dec4d_full.png",
    "path": "CSE\\out\\screenshots\\fssai.gov.in_042dec4d_full.png",
    "domain": "fssai.gov.in_042dec4d"
  },
  {
    "filename": "gailonline.com_6592479f_full.png",
    "path": "CSE\\out\\screenshots\\gailonline.com_6592479f_full.png",
    "domain": "gailonline.com_6592479f"
  },
  {
    "filename": "goa.gov.in_39a5ec08_full.png",
    "path": "CSE\\out\\screenshots\\goa.gov.in_39a5ec08_full.png",
    "domain": "goa.gov.in_39a5ec08"
  },
  {
    "filename": "gst.gov.in_5e442330_full.png",
    "path": "CSE\\out\\screenshots\\gst.gov.in_5e442330_full.png",
    "domain": "gst.gov.in_5e442330"
  },
  {
    "filename": "gujarat.gov.in_aec61662_full.png",
    "path": "CSE\\out\\screenshots\\gujarat.gov.in_aec61662_full.png",
    "domain": "gujarat.gov.in_aec61662"
  },
  {
    "filename": "hal-india.co.in_298d9eb2_full.png",
    "path": "CSE\\out\\screenshots\\hal-india.co.in_298d9eb2_full.png",
    "domain": "hal-india.co.in_298d9eb2"
  },
  {
    "filename": "haryana.gov.in_456a77a3_full.png",
    "path": "CSE\\out\\screenshots\\haryana.gov.in_456a77a3_full.png",
    "domain": "haryana.gov.in_456a77a3"
  },
  {
    "filename": "hdfcbank.com_e78f0b8d_full.png",
    "path": "CSE\\out\\screenshots\\hdfcbank.com_e78f0b8d_full.png",
    "domain": "hdfcbank.com_e78f0b8d"
  },
  {
    "filename": "hdfcergo.com_e2fca368_full.png",
    "path": "CSE\\out\\screenshots\\hdfcergo.com_e2fca368_full.png",
    "domain": "hdfcergo.com_e2fca368"
  },
  {
    "filename": "hdfclife.com_d9a030d0_full.png",
    "path": "CSE\\out\\screenshots\\hdfclife.com_d9a030d0_full.png",
    "domain": "hdfclife.com_d9a030d0"
  },
  {
    "filename": "icicibank.com_d4347fe6_full.png",
    "path": "CSE\\out\\screenshots\\icicibank.com_d4347fe6_full.png",
    "domain": "icicibank.com_d4347fe6"
  },
  {
    "filename": "icicidirect.com_9ca7b3ed_full.png",
    "path": "CSE\\out\\screenshots\\icicidirect.com_9ca7b3ed_full.png",
    "domain": "icicidirect.com_9ca7b3ed"
  },
  {
    "filename": "idbi.com_7553c3ba_full.png",
    "path": "CSE\\out\\screenshots\\idbi.com_7553c3ba_full.png",
    "domain": "idbi.com_7553c3ba"
  },
  {
    "filename": "iitb.ac.in_40a54e66_full.png",
    "path": "CSE\\out\\screenshots\\iitb.ac.in_40a54e66_full.png",
    "domain": "iitb.ac.in_40a54e66"
  },
  {
    "filename": "iitd.ac.in_8f6ea011_full.png",
    "path": "CSE\\out\\screenshots\\iitd.ac.in_8f6ea011_full.png",
    "domain": "iitd.ac.in_8f6ea011"
  },
  {
    "filename": "indianbank.in_a271e7fe_full.png",
    "path": "CSE\\out\\screenshots\\indianbank.in_a271e7fe_full.png",
    "domain": "indianbank.in_a271e7fe"
  },
  {
    "filename": "iocl.com_ec78660f_full.png",
    "path": "CSE\\out\\screenshots\\iocl.com_ec78660f_full.png",
    "domain": "iocl.com_ec78660f"
  },
  {
    "filename": "irctc.com_7476fe93_full.png",
    "path": "CSE\\out\\screenshots\\irctc.com_7476fe93_full.png",
    "domain": "irctc.com_7476fe93"
  },
  {
    "filename": "irdai.gov.in_f73086ab_full.png",
    "path": "CSE\\out\\screenshots\\irdai.gov.in_f73086ab_full.png",
    "domain": "irdai.gov.in_f73086ab"
  },
  {
    "filename": "jharkhand.gov.in_d88f12e9_full.png",
    "path": "CSE\\out\\screenshots\\jharkhand.gov.in_d88f12e9_full.png",
    "domain": "jharkhand.gov.in_d88f12e9"
  },
  {
    "filename": "maharashtra.gov.in_b8e8c42d_full.png",
    "path": "CSE\\out\\screenshots\\maharashtra.gov.in_b8e8c42d_full.png",
    "domain": "maharashtra.gov.in_b8e8c42d"
  },
  {
    "filename": "mail.gov.in_e79819ad_full.png",
    "path": "CSE\\out\\screenshots\\mail.gov.in_e79819ad_full.png",
    "domain": "mail.gov.in_e79819ad"
  },
  {
    "filename": "manipur.gov.in_a8c8449e_full.png",
    "path": "CSE\\out\\screenshots\\manipur.gov.in_a8c8449e_full.png",
    "domain": "manipur.gov.in_a8c8449e"
  },
  {
    "filename": "meghalaya.gov.in_6862f305_full.png",
    "path": "CSE\\out\\screenshots\\meghalaya.gov.in_6862f305_full.png",
    "domain": "meghalaya.gov.in_6862f305"
  },
  {
    "filename": "meity.gov.in_18c27c84_full.png",
    "path": "CSE\\out\\screenshots\\meity.gov.in_18c27c84_full.png",
    "domain": "meity.gov.in_18c27c84"
  },
  {
    "filename": "mgovcloud.in_fd6e9c1f_full.png",
    "path": "CSE\\out\\screenshots\\mgovcloud.in_fd6e9c1f_full.png",
    "domain": "mgovcloud.in_fd6e9c1f"
  },
  {
    "filename": "mizoram.gov.in_01a63093_full.png",
    "path": "CSE\\out\\screenshots\\mizoram.gov.in_01a63093_full.png",
    "domain": "mizoram.gov.in_01a63093"
  },
  {
    "filename": "mp.gov.in_d6f8d731_full.png",
    "path": "CSE\\out\\screenshots\\mp.gov.in_d6f8d731_full.png",
    "domain": "mp.gov.in_d6f8d731"
  },
  {
    "filename": "mtnl.net.in_30a10b51_full.png",
    "path": "CSE\\out\\screenshots\\mtnl.net.in_30a10b51_full.png",
    "domain": "mtnl.net.in_30a10b51"
  },
  {
    "filename": "nagaland.gov.in_5fb0f659_full.png",
    "path": "CSE\\out\\screenshots\\nagaland.gov.in_5fb0f659_full.png",
    "domain": "nagaland.gov.in_5fb0f659"
  },
  {
    "filename": "nalcoindia.com_565ab2b1_full.png",
    "path": "CSE\\out\\screenshots\\nalcoindia.com_565ab2b1_full.png",
    "domain": "nalcoindia.com_565ab2b1"
  },
  {
    "filename": "netpnb.com_0933549d_full.png",
    "path": "CSE\\out\\screenshots\\netpnb.com_0933549d_full.png",
    "domain": "netpnb.com_0933549d"
  },
  {
    "filename": "newindia.co.in_50e6b603_full.png",
    "path": "CSE\\out\\screenshots\\newindia.co.in_50e6b603_full.png",
    "domain": "newindia.co.in_50e6b603"
  },
  {
    "filename": "nhai.gov.in_6d0009ad_full.png",
    "path": "CSE\\out\\screenshots\\nhai.gov.in_6d0009ad_full.png",
    "domain": "nhai.gov.in_6d0009ad"
  },
  {
    "filename": "nic.co.in_b98ef834_full.png",
    "path": "CSE\\out\\screenshots\\nic.co.in_b98ef834_full.png",
    "domain": "nic.co.in_b98ef834"
  },
  {
    "filename": "nic.gov.in_6717bfaa_full.png",
    "path": "CSE\\out\\screenshots\\nic.gov.in_6717bfaa_full.png",
    "domain": "nic.gov.in_6717bfaa"
  },
  {
    "filename": "nitc.ac.in_d9b2c3ca_full.png",
    "path": "CSE\\out\\screenshots\\nitc.ac.in_d9b2c3ca_full.png",
    "domain": "nitc.ac.in_d9b2c3ca"
  },
  {
    "filename": "nta.ac.in_99a7d9d8_full.png",
    "path": "CSE\\out\\screenshots\\nta.ac.in_99a7d9d8_full.png",
    "domain": "nta.ac.in_99a7d9d8"
  },
  {
    "filename": "ntpc.co.in_ee482a85_full.png",
    "path": "CSE\\out\\screenshots\\ntpc.co.in_ee482a85_full.png",
    "domain": "ntpc.co.in_ee482a85"
  },
  {
    "filename": "ongcindia.com_1d5606c5_full.png",
    "path": "CSE\\out\\screenshots\\ongcindia.com_1d5606c5_full.png",
    "domain": "ongcindia.com_1d5606c5"
  },
  {
    "filename": "orientalinsurance.org.in_ab79b7bb_full.png",
    "path": "CSE\\out\\screenshots\\orientalinsurance.org.in_ab79b7bb_full.png",
    "domain": "orientalinsurance.org.in_ab79b7bb"
  },
  {
    "filename": "pnbindia.in_c7493779_full.png",
    "path": "CSE\\out\\screenshots\\pnbindia.in_c7493779_full.png",
    "domain": "pnbindia.in_c7493779"
  },
  {
    "filename": "powergrid.in_7929c3ed_full.png",
    "path": "CSE\\out\\screenshots\\powergrid.in_7929c3ed_full.png",
    "domain": "powergrid.in_7929c3ed"
  },
  {
    "filename": "punjab.gov.in_f7b1b0dd_full.png",
    "path": "CSE\\out\\screenshots\\punjab.gov.in_f7b1b0dd_full.png",
    "domain": "punjab.gov.in_f7b1b0dd"
  },
  {
    "filename": "py.gov.in_1ddc97e3_full.png",
    "path": "CSE\\out\\screenshots\\py.gov.in_1ddc97e3_full.png",
    "domain": "py.gov.in_1ddc97e3"
  },
  {
    "filename": "railtelindia.com_eb780740_full.png",
    "path": "CSE\\out\\screenshots\\railtelindia.com_eb780740_full.png",
    "domain": "railtelindia.com_eb780740"
  },
  {
    "filename": "rajasthan.gov.in_52bcf139_full.png",
    "path": "CSE\\out\\screenshots\\rajasthan.gov.in_52bcf139_full.png",
    "domain": "rajasthan.gov.in_52bcf139"
  },
  {
    "filename": "rbi.org.in_b46220be_full.png",
    "path": "CSE\\out\\screenshots\\rbi.org.in_b46220be_full.png",
    "domain": "rbi.org.in_b46220be"
  },
  {
    "filename": "recindia.nic.in_12735a9d_full.png",
    "path": "CSE\\out\\screenshots\\recindia.nic.in_12735a9d_full.png",
    "domain": "recindia.nic.in_12735a9d"
  },
  {
    "filename": "sail.co.in_2264097b_full.png",
    "path": "CSE\\out\\screenshots\\sail.co.in_2264097b_full.png",
    "domain": "sail.co.in_2264097b"
  },
  {
    "filename": "sbi.co.in_c0feeec6_full.png",
    "path": "CSE\\out\\screenshots\\sbi.co.in_c0feeec6_full.png",
    "domain": "sbi.co.in_c0feeec6"
  },
  {
    "filename": "sbicard.com_19e416c2_full.png",
    "path": "CSE\\out\\screenshots\\sbicard.com_19e416c2_full.png",
    "domain": "sbicard.com_19e416c2"
  },
  {
    "filename": "sbiepay.sbi_2fe69f1c_full.png",
    "path": "CSE\\out\\screenshots\\sbiepay.sbi_2fe69f1c_full.png",
    "domain": "sbiepay.sbi_2fe69f1c"
  },
  {
    "filename": "sebi.gov.in_a6ff308c_full.png",
    "path": "CSE\\out\\screenshots\\sebi.gov.in_a6ff308c_full.png",
    "domain": "sebi.gov.in_a6ff308c"
  },
  {
    "filename": "sikkim.gov.in_3cf51cc3_full.png",
    "path": "CSE\\out\\screenshots\\sikkim.gov.in_3cf51cc3_full.png",
    "domain": "sikkim.gov.in_3cf51cc3"
  },
  {
    "filename": "tn.gov.in_ec86b210_full.png",
    "path": "CSE\\out\\screenshots\\tn.gov.in_ec86b210_full.png",
    "domain": "tn.gov.in_ec86b210"
  },
  {
    "filename": "tripura.gov.in_1207646c_full.png",
    "path": "CSE\\out\\screenshots\\tripura.gov.in_1207646c_full.png",
    "domain": "tripura.gov.in_1207646c"
  },
  {
    "filename": "uidai.gov.in_7aca623e_full.png",
    "path": "CSE\\out\\screenshots\\uidai.gov.in_7aca623e_full.png",
    "domain": "uidai.gov.in_7aca623e"
  },
  {
    "filename": "wipro.com_99dd5fbe_full.png",
    "path": "CSE\\out\\screenshots\\wipro.com_99dd5fbe_full.png",
    "domain": "wipro.com_99dd5fbe"
  },
  {
    "filename": "yonobusiness.sbi_30671ce0_full.png",
    "path": "CSE\\out\\screenshots\\yonobusiness.sbi_30671ce0_full.png",
    "domain": "yonobusiness.sbi_30671ce0"
  }
]